{
  "paginate": 7,
  "slugs": ["ad", "soyad", "cinsiyet"],
  "titles": {
    "index": "Denemeler",
    "show": "Deneme Detay",
    "create": "Deneme Ekle",
    "edit": "Deneme Düzenle"
  },
  "routes": {
    "index": "deneme.index",
    "create": "deneme.create",
    "store": "deneme.store",
    "show": "deneme.show",
    "edit": "deneme.edit",
    "update": "deneme.update",
    "delete": "deneme.destroy"
  },
  "searchable": [
    "ad",
    "soyad"
  ],
  "fields": {
    "id": {
      "type": "hidden",
      "title": "Kimlik",
      "value": "",
      "create": false,
      "edit": false,
      "list": false,
      "detail": false
    },
    "ad": {
      "type": "text",
      "title": "Ad",
      "value": "",
      "attributes": {},
      "rules": [
        "required"
      ],
      "multiple": false,
      "create": true,
      "edit": true,
      "list": true,
      "detail": true
    },
    "soyad": {
      "type": "text",
      "title": "Soyad",
      "value": "",
      "attributes": {},
      "rules": [
        "required"
      ],
      "multiple": false,
      "create": true,
      "edit": true,
      "list": true,
      "detail": true
    },
    "hakkimda": {
      "type": "textarea",
      "title": "Hakkımda",
      "value": "",
      "attributes": {
        "rows": 5
      },
      "rules": [
        "required",
        "min:10"
      ],
      "multiple": false,
      "create": true,
      "edit": true,
      "list": false,
      "detail": true
    },
    "yas": {
      "type": "number",
      "title": "Yaş",
      "value": "",
      "attributes": {},
      "rules": [
        "required"
      ],
      "multiple": false,
      "create": true,
      "edit": true,
      "list": true,
      "detail": true
    },
    "cinsiyet": {
      "type": "radio",
      "title": "Cinsiyet",
      "value": "",
      "items": [
        "Bay",
        "Bayan",
        "Belirtmek istemiyorum"
      ],
      "attributes": {},
      "rules": [
        "required"
      ],
      "multiple": false,
      "create": true,
      "edit": true,
      "list": true,
      "detail": true
    },
    "cv": {
      "type": "file",
      "title": "CV",
      "value": "",
      "attributes": {},
      "rules": [
        "file"
      ],
      "multiple": false,
      "create": true,
      "edit": true,
      "list": true,
      "detail": true
    },
    "profile": {
      "type": "image",
      "title": "Profil Resmi",
      "value": "/admin-template/images/avatar_default.jpg",
      "attributes": {},
      "rules": [
        "mimes:jpeg,jpg,png"
      ],
      "multiple": false,
      "create": true,
      "edit": true,
      "list": false,
      "detail": true
    },
    "kontrol": {
      "type": "multi_checkbox",
      "title": "Kontrol",
      "relationship": {
        "type": "belongsToMany",
        "model": "Modules\\Deneme\\Entities\\Post",
        "keys": {
          "table": "deneme_post",
          "foreignKey": "deneme_id",
          "otherKey": "post_id"
        },
        "pluck": {
          "display": "name",
          "value": "id"
        },
        "fields": [
          "name"
        ],
        "perPage": 3
      },
      "attributes": {},
      "rules": [
        "required"
      ],
      "multiple": true,
      "create": true,
      "edit": true,
      "list": false,
      "detail": true
    },
    "resimler": {
      "type": "multi_image",
      "title": "Resimler",
      "count": 10,
      "attributes": {},
      "multiple": true,
      "create": false,
      "edit": false,
      "list": false,
      "detail": true
    },
    "durum": {
      "type": "checkbox",
      "title": "Onaylı",
      "label": "18 yaşından büyük olduğumu kabul ediyorum.",
      "rules": [
        "accepted"
      ],
      "multiple": false,
      "create": true,
      "edit": true,
      "list": false,
      "detail": true
    },
    "count_id": {
      "id": "count_id",
      "type": "select",
      "title": "Öylesine",
      "name": "count_id",
      "value": null,
      "rules": [
        "required"
      ],
      "multiple": false,
      "relationship": {
        "type": "hasOne",
        "model": "Modules\\Sales\\Entities\\SaleInfo",
        "keys": {
          "foreignKey": "id",
          "otherKey": "count_id"
        },
        "pluck": {
          "display": "buy_price",
          "value": "id"
        },
        "fields": [
          "buy_price"
        ]
      },
      "attributes": {},
      "create": true,
      "edit": true,
      "list": true,
      "detail": true
    },
    "datee": {
      "type": "date",
      "title": "Bilmem Tarihi",
      "rules": [
        "required"
      ],
      "multiple": false,
      "create": true,
      "edit": true,
      "list": true,
      "detail": true
    },
    "dateetime": {
      "type": "datetime",
      "title": "Datee Tarihi",
      "name": "created_at",
      "rules": [
        "required"
      ],
      "multiple": false,
      "create": true,
      "edit": true,
      "list": false,
      "detail": true
    },
    "created_at": {
      "type": "datetime",
      "title": "Eklenme Tarihi",
      "name": "created_at",
      "rules": [
        "required"
      ],
      "multiple": false,
      "create": false,
      "edit": false,
      "list": false,
      "detail": true
    },
    "updated_at": {
      "type": "datetime",
      "title": "Son Düzenlenme Tarihi",
      "name": "updated_at",
      "rules": [
        "required"
      ],
      "multiple": false,
      "create": false,
      "edit": false,
      "list": false,
      "detail": false
    }
  }
}
