{
    "searchable": [
        "ad"
    ],
    "fields": {
        "id": {
            "id": "id",
            "type": "hidden",
            "title": "Kimlik",
            "name": "id",
            "value": "",
            "create": false,
            "edit": true,
            "list": false,
            "detail": true
        },
        "name": {
            "id": "name",
            "type": "text",
            "title": "Ad",
            "name": "name",
            "value": "",
            "attributes": [],
            "multiple": false,
            "create": true,
            "edit": true,
            "list": true,
            "detail": true
        },
        "denemeler": {
            "id": "denemeler",
            "type": "multi_checkbox",
            "title": "Denemeler",
            "name": "denemeler",
            "relationship": {
                "type": "belongsToMany",
                "model": "Modules\\Deneme\\Entities\\Deneme",
                "fields": [
                    "id",
                    "ad",
                    "yas",
                    "soyad"
                ],
                "keys": {
                    "table": "deneme_post",
                    "foreignKey": "post_id",
                    "otherKey": "deneme_id"
                },
                "perPage": 5
            },
            "attributes": [],
            "multiple": true,
            "create": true,
            "edit": true,
            "list": true,
            "detail": true
        }
    }
}
